Workbook

Sheet 01_Executive_Dashboard
A1: EXECUTIVE FINANCIAL DASHBOARD & MANAGEMENT SCORECARD
A2: FY 2026 Strategic Plan: 12-Month Projections, Operating Margins, Liquidity Runway & BvA Performance
B4: ANNUAL FORECAST REVENUE | D4: FORECAST GROSS MARGIN | F4: ANNUAL EBITDA | H4: NET CASH CHANGE (FY) | J4: ENDING CASH BALANCE (M12)
B5: ='03_12M_P&L_Forecast'!O10 | D5: ='03_12M_P&L_Forecast'!O18 | F5: ='03_12M_P&L_Forecast'!O28 | H5: ='04_Monthly_Cash_Flow'!O19 | J5: ='04_Monthly_Cash_Flow'!O22
B6: Target: $1.65M (+18% YoY) | D6: Benchmark: > 75% Tech SaaS | F6: Operating cash generation | H6: Full-year net cash build | J6: Safety reserve intact
B8: QUARTERLY FINANCIAL PERFORMANCE SUMMARY (FY 2026 ROLL-UP)
B9: Financial Metric / Line Item | C9: Q1 2026 | D9: Q2 2026 | E9: Q3 2026 | F9: Q4 2026 | G9: FY 2026 Total | H9: % of Rev
B10: Gross Revenue | C10: =SUM('03_12M_P&L_Forecast'!C10:E10) | D10: =SUM('03_12M_P&L_Forecast'!F10:H10) | E10: =SUM('03_12M_P&L_Forecast'!I10:K10) | F10: =SUM('03_12M_P&L_Forecast'!L10:N10) | G10: ='03_12M_P&L_Forecast'!O10 | H10: 1
B11: Cost of Goods Sold (COGS) | C11: =SUM('03_12M_P&L_Forecast'!C16:E16) | D11: =SUM('03_12M_P&L_Forecast'!F16:H16) | E11: =SUM('03_12M_P&L_Forecast'!I16:K16) | F11: =SUM('03_12M_P&L_Forecast'!L16:N16) | G11: ='03_12M_P&L_Forecast'!O16 | H11: =G11/$G$10
B12: Gross Profit | C12: =C10-C11 | D12: =D10-D11 | E12: =E10-E11 | F12: =F10-F11 | G12: =G10-G11 | H12: =G12/$G$10
B13: Operating Expenses (OpEx) | C13: =SUM('03_12M_P&L_Forecast'!C27:E27) | D13: =SUM('03_12M_P&L_Forecast'!F27:H27) | E13: =SUM('03_12M_P&L_Forecast'!I27:K27) | F13: =SUM('03_12M_P&L_Forecast'!L27:N27) | G13: ='03_12M_P&L_Forecast'!O27 | H13: =G13/$G$10
B14: EBITDA | C14: =C12-C13 | D14: =D12-D13 | E14: =E12-E13 | F14: =F12-F13 | G14: =G12-G13 | H14: =G14/$G$10
B15: Net Profit After Tax | C15: =SUM('03_12M_P&L_Forecast'!C32:E32) | D15: =SUM('03_12M_P&L_Forecast'!F32:H32) | E15: =SUM('03_12M_P&L_Forecast'!I32:K32) | F15: =SUM('03_12M_P&L_Forecast'!L32:N32) | G15: ='03_12M_P&L_Forecast'!O32 | H15: =G15/$G$10
B16: Ending Cash Liquidity | C16: ='04_Monthly_Cash_Flow'!E22 | D16: ='04_Monthly_Cash_Flow'!H22 | E16: ='04_Monthly_Cash_Flow'!K22 | F16: ='04_Monthly_Cash_Flow'!N22 | G16: ='04_Monthly_Cash_Flow'!O22 | H16: -
B18: C-SUITE STRATEGIC OBSERVATIONS & EXECUTIVE DIRECTIVES
B19: Revenue Acceleration | C19: Enterprise Platform Licenses (+12% vs budget) are the fastest scaling high-margin driver. Accelerate AE hiring in Q2 to maintain outbound pipeline.
B20: Gross Margin Defense | C20: COGS averages 20.3% across product lines. Consolidate AWS cloud instances to reserve commitments by Month 4 to unlock 15% hosting savings.
B21: OpEx Discipline & Payroll | C21: Payroll accounts for 58% of total OpEx. The hiring ramp of junior developers in Month 4 is fully funded by organic operational cash flow.
B22: Working Capital & Runway | C22: With Day 1 cash of $125k and Q4 ending cash of $310k+, the company achieves positive cash generation by Month 3 and has ZERO external dilution need.

Sheet 02_Assumptions_&_Drivers
A1: FINANCIAL ASSUMPTIONS & BUSINESS PLANNING DRIVERS (FY 2026)
A2: Key Operational Drivers, Unit Economics, Headcount, Cost Structure & Working Capital Terms
B4: Color Standard Legend: | C4: BLUE FONT / GREEN CELL = Dynamic User Input | E4: BLACK FONT = Dynamic Calculation
B6: 1. REVENUE STREAMS & UNIT PRICING DRIVERS
B7: Driver ID | C7: Revenue Stream / Service Line | D7: Starting Monthly Units | E7: Monthly Growth Rate | F7: Base Unit Price | G7: COGS Direct Cost %
B8: REV-01 | C8: SaaS Subscriptions (Pro Tier) | D8: 150 | E8: 0.08 | F8: 120 | G8: 0.12
B9: REV-02 | C9: Enterprise Platform Licenses | D9: 15 | E9: 0.05 | F9: 2500 | G9: 0.18
B10: REV-03 | C10: Professional Implementation & Onboarding | D10: 8 | E10: 0.04 | F10: 3800 | G10: 0.35
B11: REV-04 | C11: Premium Managed Services & SLA | D11: 25 | E11: 0.06 | F11: 650 | G11: 0.2
B13: 2. HEADCOUNT ROSTER & PAYROLL ASSUMPTIONS
B14: Role Code | C14: Role Title | D14: Department | E14: Start Month | F14: Monthly Base Salary | G14: Benefits & Taxes %
B15: EMP-01 | C15: Senior Full-Stack Engineer | D15: Engineering / R&D | E15: 1 | F15: 7500 | G15: 0.2
B16: EMP-02 | C16: Backend & Cloud Architect | D16: Engineering / R&D | E16: 1 | F16: 8000 | G16: 0.2
B17: EMP-03 | C17: Junior Data Engineer | D17: Engineering / R&D | E17: 4 | F17: 4500 | G17: 0.18
B18: EMP-04 | C18: Account Executive / B2B Sales | D18: Sales & Marketing | E18: 1 | F18: 5500 | G18: 0.18
B19: EMP-05 | C19: Growth Marketing Specialist | D19: Sales & Marketing | E19: 3 | F19: 4800 | G19: 0.18
B20: EMP-06 | C20: Operations & FP&A Lead | D20: General & Admin | E20: 1 | F20: 6500 | G20: 0.2
B21: EMP-07 | C21: Customer Success Specialist | D21: Customer Support | E21: 2 | F21: 3800 | G21: 0.18
B23: 3. OPERATING EXPENSES (OpEx) & OVERHEAD
B24: Exp Code | C24: Expense Category | D24: Cost Type | E24: Monthly Base Budget | F24: MoM Inflation / Scale % | G24: Notes
B25: OPX-01 | C25: Paid Digital Marketing & Ads | D25: Variable | E25: 4500 | F25: 0.03 | G25: Scales with customer acquisition targets
B26: OPX-02 | C26: Cloud Infrastructure (AWS/GCP) | D26: Semi-Variable | E26: 2200 | F26: 0.04 | G26: Server compute, storage, egress bandwidth
B27: OPX-03 | C27: Software Subscriptions & SaaS Tools | D27: Fixed | E27: 1850 | F27: 0.01 | G27: CRM, GitHub, Slack, Notion, Accounting
B28: OPX-04 | C28: Office Rent & Utilities | D28: Fixed | E28: 3200 | F28: 0 | G28: HQ Co-working & physical facility lease
B29: OPX-05 | C29: Legal, Audit & Professional Fees | D29: Fixed | E29: 1500 | F29: 0 | G29: Corporate compliance, tax filings, legal retainers
B30: OPX-06 | C30: Travel, Events & Client Entertainment | D30: Variable | E30: 1200 | F30: 0.02 | G30: Industry trade shows & prospect meetings
B32: 4. WORKING CAPITAL, TAX & CASH RUNWAY DRIVERS
B33: Param Code | C33: Parameter Description | D33: Assumed Value | E33: Unit / Metric | F33: Model Reference | G33: Strategic Impact
B34: WC-01 | C34: Starting Cash Balance (Day 1) | D34: 125000 | E34: $ USD | F34: Cash Flow Tab (M1) | G34: Seed / Operational Cash Buffer
B35: WC-02 | C35: Days Sales Outstanding (DSO - Receivables) | D35: 30 | E35: Days (1 Mo Lag) | F35: Cash Flow Collections | G35: Customer payment collection timing
B36: WC-03 | C36: Days Payable Outstanding (DPO - Payables) | D36: 30 | E36: Days (1 Mo Lag) | F36: Cash Flow Vendor Payouts | G36: Supplier payment credit terms
B37: WC-04 | C37: Corporate Income Tax Rate | D37: 0.25 | E37: % of EBT | F37: P&L Tax Calculation | G37: Accrued on positive earnings
B38: WC-05 | C38: Monthly Depreciation Rate | D38: 850 | E38: $ USD / Month | F38: P&L Non-Cash Expense | G38: Hardware & IT Equipment depreciation
B39: WC-06 | C39: Planned CapEx (Q2 Upgrade) | D39: 15000 | E39: $ USD (M5) | F39: Cash Flow Investing | G39: Core database cluster expansion
B40: WC-07 | C40: Planned CapEx (Q4 Hardware) | D40: 12000 | E40: $ USD (M10) | F40: Cash Flow Investing | G40: Development laptops & test devices
B41: WC-08 | C41: Target Minimum Cash Reserve | D41: 40000 | E41: $ USD | F41: Dashboard Safety Trigger | G41: 3-Month critical buffer threshold

Sheet 03_12M_P&L_Forecast
A1: 12-MONTH PROFIT & LOSS (P&L) PROJECTION & OPERATING BUDGET
A2: Comprehensive Income Statement Model: Revenue, Direct COGS, Departmental OpEx, EBITDA & Net Profit
B4: Line Item / Accounting Code | C4: M1 (2026) | D4: M2 (2026) | E4: M3 (2026) | F4: M4 (2026) | G4: M5 (2026) | H4: M6 (2026) | I4: M7 (2026) | J4: M8 (2026) | K4: M9 (2026) | L4: M10 (2026) | M4: M11 (2026) | N4: M12 (2026) | O4: FY 2026 Total | P4: % of Revenue
B5: 1. GROSS REVENUE
B6: SaaS Subscriptions (Pro Tier) | C6: ='02_Assumptions_&_Drivers'!D8*'02_Assumptions_&_Drivers'!F8 | D6: =C6*(1+'02_Assumptions_&_Drivers'!E8) | E6: =D6*(1+'02_Assumptions_&_Drivers'!E8) | F6: =E6*(1+'02_Assumptions_&_Drivers'!E8) | G6: =F6*(1+'02_Assumptions_&_Drivers'!E8) | H6: =G6*(1+'02_Assumptions_&_Drivers'!E8) | I6: =H6*(1+'02_Assumptions_&_Drivers'!E8) | J6: =I6*(1+'02_Assumptions_&_Drivers'!E8) | K6: =J6*(1+'02_Assumptions_&_Drivers'!E8) | L6: =K6*(1+'02_Assumptions_&_Drivers'!E8) | M6: =L6*(1+'02_Assumptions_&_Drivers'!E8) | N6: =M6*(1+'02_Assumptions_&_Drivers'!E8) | O6: =SUM(C6:N6) | P6: =O6/$O$10
B7: Enterprise Platform Licenses | C7: ='02_Assumptions_&_Drivers'!D9*'02_Assumptions_&_Drivers'!F9 | D7: =C7*(1+'02_Assumptions_&_Drivers'!E9) | E7: =D7*(1+'02_Assumptions_&_Drivers'!E9) | F7: =E7*(1+'02_Assumptions_&_Drivers'!E9) | G7: =F7*(1+'02_Assumptions_&_Drivers'!E9) | H7: =G7*(1+'02_Assumptions_&_Drivers'!E9) | I7: =H7*(1+'02_Assumptions_&_Drivers'!E9) | J7: =I7*(1+'02_Assumptions_&_Drivers'!E9) | K7: =J7*(1+'02_Assumptions_&_Drivers'!E9) | L7: =K7*(1+'02_Assumptions_&_Drivers'!E9) | M7: =L7*(1+'02_Assumptions_&_Drivers'!E9) | N7: =M7*(1+'02_Assumptions_&_Drivers'!E9) | O7: =SUM(C7:N7) | P7: =O7/$O$10
B8: Professional Implementation & Onboarding | C8: ='02_Assumptions_&_Drivers'!D10*'02_Assumptions_&_Drivers'!F10 | D8: =C8*(1+'02_Assumptions_&_Drivers'!E10) | E8: =D8*(1+'02_Assumptions_&_Drivers'!E10) | F8: =E8*(1+'02_Assumptions_&_Drivers'!E10) | G8: =F8*(1+'02_Assumptions_&_Drivers'!E10) | H8: =G8*(1+'02_Assumptions_&_Drivers'!E10) | I8: =H8*(1+'02_Assumptions_&_Drivers'!E10) | J8: =I8*(1+'02_Assumptions_&_Drivers'!E10) | K8: =J8*(1+'02_Assumptions_&_Drivers'!E10) | L8: =K8*(1+'02_Assumptions_&_Drivers'!E10) | M8: =L8*(1+'02_Assumptions_&_Drivers'!E10) | N8: =M8*(1+'02_Assumptions_&_Drivers'!E10) | O8: =SUM(C8:N8) | P8: =O8/$O$10
B9: Premium Managed Services & SLA | C9: ='02_Assumptions_&_Drivers'!D11*'02_Assumptions_&_Drivers'!F11 | D9: =C9*(1+'02_Assumptions_&_Drivers'!E11) | E9: =D9*(1+'02_Assumptions_&_Drivers'!E11) | F9: =E9*(1+'02_Assumptions_&_Drivers'!E11) | G9: =F9*(1+'02_Assumptions_&_Drivers'!E11) | H9: =G9*(1+'02_Assumptions_&_Drivers'!E11) | I9: =H9*(1+'02_Assumptions_&_Drivers'!E11) | J9: =I9*(1+'02_Assumptions_&_Drivers'!E11) | K9: =J9*(1+'02_Assumptions_&_Drivers'!E11) | L9: =K9*(1+'02_Assumptions_&_Drivers'!E11) | M9: =L9*(1+'02_Assumptions_&_Drivers'!E11) | N9: =M9*(1+'02_Assumptions_&_Drivers'!E11) | O9: =SUM(C9:N9) | P9: =O9/$O$10
B10: TOTAL GROSS REVENUE | C10: =SUM(C6:C9) | D10: =SUM(D6:D9) | E10: =SUM(E6:E9) | F10: =SUM(F6:F9) | G10: =SUM(G6:G9) | H10: =SUM(H6:H9) | I10: =SUM(I6:I9) | J10: =SUM(J6:J9) | ... O10: =SUM(O6:O9) | P10: 1
B11: 2. COST OF GOODS SOLD (COGS)
B12: Direct Hosting & Cloud Infrastructure | C12: =C6*'02_Assumptions_&_Drivers'!G8 | D12: =D6*'02_Assumptions_&_Drivers'!G8 | E12: =E6*'02_Assumptions_&_Drivers'!G8 | F12: =F6*'02_Assumptions_&_Drivers'!G8 | G12: =G6*'02_Assumptions_&_Drivers'!G8 | H12: =H6*'02_Assumptions_&_Drivers'!G8 | I12: =I6*'02_Assumptions_&_Drivers'!G8 | J12: =J6*'02_Assumptions_&_Drivers'!G8 | K12: =K6*'02_Assumptions_&_Drivers'!G8 | L12: =L6*'02_Assumptions_&_Drivers'!G8 | M12: =M6*'02_Assumptions_&_Drivers'!G8 | N12: =N6*'02_Assumptions_&_Drivers'!G8 | O12: =SUM(C12:N12) | P12: =O12/$O$10
B13: License Royalties & Third-Party APIs | C13: =C7*'02_Assumptions_&_Drivers'!G9 | D13: =D7*'02_Assumptions_&_Drivers'!G9 | E13: =E7*'02_Assumptions_&_Drivers'!G9 | F13: =F7*'02_Assumptions_&_Drivers'!G9 | G13: =G7*'02_Assumptions_&_Drivers'!G9 | H13: =H7*'02_Assumptions_&_Drivers'!G9 | I13: =I7*'02_Assumptions_&_Drivers'!G9 | J13: =J7*'02_Assumptions_&_Drivers'!G9 | K13: =K7*'02_Assumptions_&_Drivers'!G9 | L13: =L7*'02_Assumptions_&_Drivers'!G9 | M13: =M7*'02_Assumptions_&_Drivers'!G9 | N13: =N7*'02_Assumptions_&_Drivers'!G9 | O13: =SUM(C13:N13) | P13: =O13/$O$10
B14: Contract Implementation Engineering | C14: =C8*'02_Assumptions_&_Drivers'!G10 | D14: =D8*'02_Assumptions_&_Drivers'!G10 | E14: =E8*'02_Assumptions_&_Drivers'!G10 | F14: =F8*'02_Assumptions_&_Drivers'!G10 | G14: =G8*'02_Assumptions_&_Drivers'!G10 | H14: =H8*'02_Assumptions_&_Drivers'!G10 | I14: =I8*'02_Assumptions_&_Drivers'!G10 | J14: =J8*'02_Assumptions_&_Drivers'!G10 | K14: =K8*'02_Assumptions_&_Drivers'!G10 | L14: =L8*'02_Assumptions_&_Drivers'!G10 | M14: =M8*'02_Assumptions_&_Drivers'!G10 | N14: =N8*'02_Assumptions_&_Drivers'!G10 | O14: =SUM(C14:N14) | P14: =O14/$O$10
B15: Support Engineering & SLA Delivery | C15: =C9*'02_Assumptions_&_Drivers'!G11 | D15: =D9*'02_Assumptions_&_Drivers'!G11 | E15: =E9*'02_Assumptions_&_Drivers'!G11 | F15: =F9*'02_Assumptions_&_Drivers'!G11 | G15: =G9*'02_Assumptions_&_Drivers'!G11 | H15: =H9*'02_Assumptions_&_Drivers'!G11 | I15: =I9*'02_Assumptions_&_Drivers'!G11 | J15: =J9*'02_Assumptions_&_Drivers'!G11 | K15: =K9*'02_Assumptions_&_Drivers'!G11 | L15: =L9*'02_Assumptions_&_Drivers'!G11 | M15: =M9*'02_Assumptions_&_Drivers'!G11 | N15: =N9*'02_Assumptions_&_Drivers'!G11 | O15: =SUM(C15:N15) | P15: =O15/$O$10
B16: TOTAL COST OF GOODS SOLD | C16: =SUM(C12:C15) | D16: =SUM(D12:D15) | E16: =SUM(E12:E15) | F16: =SUM(F12:F15) | G16: =SUM(G12:G15) | H16: =SUM(H12:H15) | I16: =SUM(I12:I15) | J16: =SUM(J12:J15) | ... O16: =SUM(O12:O15) | P16: =O16/$O$10
B17: GROSS PROFIT | C17: =C10-C16 | D17: =D10-D16 | E17: =E10-E16 | F17: =F10-F16 | G17: =G10-G16 | H17: =H10-H16 | I17: =I10-I16 | J17: =J10-J16 | ... O17: =O10-O16 | P17: =O17/$O$10
B18: Gross Margin % | C18: =C17/C10 | D18: =D17/D10 | E18: =E17/E10 | F18: =F17/F10 | G18: =G17/G10 | H18: =H17/H10 | I18: =I17/I10 | J18: =J17/J10 | ... O18: =O17/O10
B19: 3. OPERATING EXPENSES (OpEx)
B20: Salaries, Wages & Benefits | C20: =SUMPRODUCT(('02_Assumptions_&_Drivers'!$E$16:$E$22<=1)*('02_Assumptions_&_Drivers'!$F$16:$F$22*(1+'02_Assumptions_&_Drivers'!$G$16:$G$22))) | D20: =SUMPRODUCT(('02_Assumptions_&_Drivers'!$E$16:$E$22<=2)*('02_Assumptions_&_Drivers'!$F$16:$F$22*(1+'02_Assumptions_&_Drivers'!$G$16:$G$22))) | E20: =SUMPRODUCT(('02_Assumptions_&_Drivers'!$E$16:$E$22<=3)*('02_Assumptions_&_Drivers'!$F$16:$F$22*(1+'02_Assumptions_&_Drivers'!$G$16:$G$22))) | F20: =SUMPRODUCT(('02_Assumptions_&_Drivers'!$E$16:$E$22<=4)*('02_Assumptions_&_Drivers'!$F$16:$F$22*(1+'02_Assumptions_&_Drivers'!$G$16:$G$22))) | G20: =SUMPRODUCT(('02_Assumptions_&_Drivers'!$E$16:$E$22<=5)*('02_Assumptions_&_Drivers'!$F$16:$F$22*(1+'02_Assumptions_&_Drivers'!$G$16:$G$22))) | H20: =SUMPRODUCT(('02_Assumptions_&_Drivers'!$E$16:$E$22<=6)*('02_Assumptions_&_Drivers'!$F$16:$F$22*(1+'02_Assumptions_&_Drivers'!$G$16:$G$22))) | I20: =SUMPRODUCT(('02_Assumptions_&_Drivers'!$E$16:$E$22<=7)*('02_Assumptions_&_Drivers'!$F$16:$F$22*(1+'02_Assumptions_&_Drivers'!$G$16:$G$22))) | J20: =SUMPRODUCT(('02_Assumptions_&_Drivers'!$E$16:$E$22<=8)*('02_Assumptions_&_Drivers'!$F$16:$F$22*(1+'02_Assumptions_&_Drivers'!$G$16:$G$22))) | K20: =SUMPRODUCT(('02_Assumptions_&_Drivers'!$E$16:$E$22<=9)*('02_Assumptions_&_Drivers'!$F$16:$F$22*(1+'02_Assumptions_&_Drivers'!$G$16:$G$22))) | L20: =SUMPRODUCT(('02_Assumptions_&_Drivers'!$E$16:$E$22<=10)*('02_Assumptions_&_Drivers'!$F$16:$F$22*(1+'02_Assumptions_&_Drivers'!$G$16:$G$22))) | M20: =SUMPRODUCT(('02_Assumptions_&_Drivers'!$E$16:$E$22<=11)*('02_Assumptions_&_Drivers'!$F$16:$F$22*(1+'02_Assumptions_&_Drivers'!$G$16:$G$22))) | N20: =SUMPRODUCT(('02_Assumptions_&_Drivers'!$E$16:$E$22<=12)*('02_Assumptions_&_Drivers'!$F$16:$F$22*(1+'02_Assumptions_&_Drivers'!$G$16:$G$22))) | O20: =SUM(C20:N20) | P20: =O20/$O$10
B21: Paid Digital Marketing & Ads | C21: ='02_Assumptions_&_Drivers'!E27 | D21: =C21*(1+'02_Assumptions_&_Drivers'!F27) | E21: =D21*(1+'02_Assumptions_&_Drivers'!F27) | F21: =E21*(1+'02_Assumptions_&_Drivers'!F27) | G21: =F21*(1+'02_Assumptions_&_Drivers'!F27) | H21: =G21*(1+'02_Assumptions_&_Drivers'!F27) | I21: =H21*(1+'02_Assumptions_&_Drivers'!F27) | J21: =I21*(1+'02_Assumptions_&_Drivers'!F27) | K21: =J21*(1+'02_Assumptions_&_Drivers'!F27) | L21: =K21*(1+'02_Assumptions_&_Drivers'!F27) | M21: =L21*(1+'02_Assumptions_&_Drivers'!F27) | N21: =M21*(1+'02_Assumptions_&_Drivers'!F27) | O21: =SUM(C21:N21) | P21: =O21/$O$10
B22: Cloud Infrastructure (Internal/Ops) | C22: ='02_Assumptions_&_Drivers'!E28 | D22: =C22*(1+'02_Assumptions_&_Drivers'!F28) | E22: =D22*(1+'02_Assumptions_&_Drivers'!F28) | F22: =E22*(1+'02_Assumptions_&_Drivers'!F28) | G22: =F22*(1+'02_Assumptions_&_Drivers'!F28) | H22: =G22*(1+'02_Assumptions_&_Drivers'!F28) | I22: =H22*(1+'02_Assumptions_&_Drivers'!F28) | J22: =I22*(1+'02_Assumptions_&_Drivers'!F28) | K22: =J22*(1+'02_Assumptions_&_Drivers'!F28) | L22: =K22*(1+'02_Assumptions_&_Drivers'!F28) | M22: =L22*(1+'02_Assumptions_&_Drivers'!F28) | N22: =M22*(1+'02_Assumptions_&_Drivers'!F28) | O22: =SUM(C22:N22) | P22: =O22/$O$10
B23: Software Subscriptions & SaaS Tools | C23: ='02_Assumptions_&_Drivers'!E29 | D23: =C23*(1+'02_Assumptions_&_Drivers'!F29) | E23: =D23*(1+'02_Assumptions_&_Drivers'!F29) | F23: =E23*(1+'02_Assumptions_&_Drivers'!F29) | G23: =F23*(1+'02_Assumptions_&_Drivers'!F29) | H23: =G23*(1+'02_Assumptions_&_Drivers'!F29) | I23: =H23*(1+'02_Assumptions_&_Drivers'!F29) | J23: =I23*(1+'02_Assumptions_&_Drivers'!F29) | K23: =J23*(1+'02_Assumptions_&_Drivers'!F29) | L23: =K23*(1+'02_Assumptions_&_Drivers'!F29) | M23: =L23*(1+'02_Assumptions_&_Drivers'!F29) | N23: =M23*(1+'02_Assumptions_&_Drivers'!F29) | O23: =SUM(C23:N23) | P23: =O23/$O$10
B24: Office Lease & Facilities | C24: ='02_Assumptions_&_Drivers'!E30 | D24: =C24*(1+'02_Assumptions_&_Drivers'!F30) | E24: =D24*(1+'02_Assumptions_&_Drivers'!F30) | F24: =E24*(1+'02_Assumptions_&_Drivers'!F30) | G24: =F24*(1+'02_Assumptions_&_Drivers'!F30) | H24: =G24*(1+'02_Assumptions_&_Drivers'!F30) | I24: =H24*(1+'02_Assumptions_&_Drivers'!F30) | J24: =I24*(1+'02_Assumptions_&_Drivers'!F30) | K24: =J24*(1+'02_Assumptions_&_Drivers'!F30) | L24: =K24*(1+'02_Assumptions_&_Drivers'!F30) | M24: =L24*(1+'02_Assumptions_&_Drivers'!F30) | N24: =M24*(1+'02_Assumptions_&_Drivers'!F30) | O24: =SUM(C24:N24) | P24: =O24/$O$10
B25: Legal, Audit & Professional Services | C25: ='02_Assumptions_&_Drivers'!E31 | D25: =C25*(1+'02_Assumptions_&_Drivers'!F31) | E25: =D25*(1+'02_Assumptions_&_Drivers'!F31) | F25: =E25*(1+'02_Assumptions_&_Drivers'!F31) | G25: =F25*(1+'02_Assumptions_&_Drivers'!F31) | H25: =G25*(1+'02_Assumptions_&_Drivers'!F31) | I25: =H25*(1+'02_Assumptions_&_Drivers'!F31) | J25: =I25*(1+'02_Assumptions_&_Drivers'!F31) | K25: =J25*(1+'02_Assumptions_&_Drivers'!F31) | L25: =K25*(1+'02_Assumptions_&_Drivers'!F31) | M25: =L25*(1+'02_Assumptions_&_Drivers'!F31) | N25: =M25*(1+'02_Assumptions_&_Drivers'!F31) | O25: =SUM(C25:N25) | P25: =O25/$O$10
B26: Travel, Events & Business Development | C26: ='02_Assumptions_&_Drivers'!E32 | D26: =C26*(1+'02_Assumptions_&_Drivers'!F32) | E26: =D26*(1+'02_Assumptions_&_Drivers'!F32) | F26: =E26*(1+'02_Assumptions_&_Drivers'!F32) | G26: =F26*(1+'02_Assumptions_&_Drivers'!F32) | H26: =G26*(1+'02_Assumptions_&_Drivers'!F32) | I26: =H26*(1+'02_Assumptions_&_Drivers'!F32) | J26: =I26*(1+'02_Assumptions_&_Drivers'!F32) | K26: =J26*(1+'02_Assumptions_&_Drivers'!F32) | L26: =K26*(1+'02_Assumptions_&_Drivers'!F32) | M26: =L26*(1+'02_Assumptions_&_Drivers'!F32) | N26: =M26*(1+'02_Assumptions_&_Drivers'!F32) | O26: =SUM(C26:N26) | P26: =O26/$O$10
B27: TOTAL OPERATING EXPENSES (OpEx) | C27: =SUM(C20:C26) | D27: =SUM(D20:D26) | E27: =SUM(E20:E26) | F27: =SUM(F20:F26) | G27: =SUM(G20:G26) | H27: =SUM(H20:H26) | I27: =SUM(I20:I26) | J27: =SUM(J20:J26) | ... O27: =SUM(O20:O26) | P27: =O27/$O$10
B28: EBITDA (Operating Earnings) | C28: =C17-C27 | D28: =D17-D27 | E28: =E17-E27 | F28: =F17-F27 | G28: =G17-G27 | H28: =H17-H27 | I28: =I17-I27 | J28: =J17-J27 | ... O28: =O17-O27 | P28: =O28/$O$10
B29: Less: Depreciation & Amortization | C29: ='02_Assumptions_&_Drivers'!$D$41 | D29: ='02_Assumptions_&_Drivers'!$D$41 | E29: ='02_Assumptions_&_Drivers'!$D$41 | F29: ='02_Assumptions_&_Drivers'!$D$41 | G29: ='02_Assumptions_&_Drivers'!$D$41 | H29: ='02_Assumptions_&_Drivers'!$D$41 | I29: ='02_Assumptions_&_Drivers'!$D$41 | J29: ='02_Assumptions_&_Drivers'!$D$41 | ... N29: ='02_Assumptions_&_Drivers'!$D$41 | O29: =SUM(C29:N29) | P29: =O29/$O$10
B30: EBIT (Operating Income) | C30: =C28-C29 | D30: =D28-D29 | E30: =E28-E29 | F30: =F28-F29 | G30: =G28-G29 | H30: =H28-H29 | I30: =I28-I29 | J30: =J28-J29 | ... O30: =O28-O29 | P30: =O30/$O$10
B31: Less: Corporate Income Tax (25%) | C31: =IF(C30>0,C30*'02_Assumptions_&_Drivers'!$D$40,0) | D31: =IF(D30>0,D30*'02_Assumptions_&_Drivers'!$D$40,0) | E31: =IF(E30>0,E30*'02_Assumptions_&_Drivers'!$D$40,0) | F31: =IF(F30>0,F30*'02_Assumptions_&_Drivers'!$D$40,0) | G31: =IF(G30>0,G30*'02_Assumptions_&_Drivers'!$D$40,0) | H31: =IF(H30>0,H30*'02_Assumptions_&_Drivers'!$D$40,0) | I31: =IF(I30>0,I30*'02_Assumptions_&_Drivers'!$D$40,0) | J31: =IF(J30>0,J30*'02_Assumptions_&_Drivers'!$D$40,0) | ... N31: =IF(N30>0,N30*'02_Assumptions_&_Drivers'!$D$40,0) | O31: =SUM(C31:N31) | P31: =O31/$O$10
B32: NET PROFIT / (LOSS) | C32: =C30-C31 | D32: =D30-D31 | E32: =E30-E31 | F32: =F30-F31 | G32: =G30-G31 | H32: =H30-H31 | I32: =I30-I31 | J32: =J30-J31 | ... O32: =O30-O31 | P32: =O32/$O$10
B33: Net Margin % | C33: =C32/C10 | D33: =D32/D10 | E33: =E32/E10 | F33: =F32/F10 | G33: =G32/G10 | H33: =H32/H10 | I33: =I32/I10 | J33: =J32/J10 | ... O33: =O32/O10

Sheet 04_Monthly_Cash_Flow
A1: 12-MONTH MONTHLY CASH-FLOW STATEMENT & LIQUIDITY FORECAST
A2: Direct Cash Flow: Operating Cash Collections, Vendor Disbursements, CapEx, Net Burn & Cash Runway
B4: Cash Flow Line Item / Activity | C4: M1 (2026) | D4: M2 (2026) | E4: M3 (2026) | F4: M4 (2026) | G4: M5 (2026) | H4: M6 (2026) | I4: M7 (2026) | J4: M8 (2026) | K4: M9 (2026) | L4: M10 (2026) | M4: M11 (2026) | N4: M12 (2026) | O4: FY 2026 Total
B5: 1. OPERATING CASH INFLOWS (COLLECTIONS)
B6: Customer Cash Receipts (Collections) | C6: ='03_12M_P&L_Forecast'!C10*0.85 | D6: ='03_12M_P&L_Forecast'!D10*0.80+'03_12M_P&L_Forecast'!C10*0.20 | E6: ='03_12M_P&L_Forecast'!E10*0.80+'03_12M_P&L_Forecast'!D10*0.20 | F6: ='03_12M_P&L_Forecast'!F10*0.80+'03_12M_P&L_Forecast'!E10*0.20 | G6: ='03_12M_P&L_Forecast'!G10*0.80+'03_12M_P&L_Forecast'!F10*0.20 | H6: ='03_12M_P&L_Forecast'!H10*0.80+'03_12M_P&L_Forecast'!G10*0.20 | I6: ='03_12M_P&L_Forecast'!I10*0.80+'03_12M_P&L_Forecast'!H10*0.20 | J6: ='03_12M_P&L_Forecast'!J10*0.80+'03_12M_P&L_Forecast'!I10*0.20 | K6: ='03_12M_P&L_Forecast'!K10*0.80+'03_12M_P&L_Forecast'!J10*0.20 | ... N6: ='03_12M_P&L_Forecast'!N10*0.80+'03_12M_P&L_Forecast'!M10*0.20 | O6: =SUM(C6:N6)
B7: TOTAL OPERATING CASH INFLOWS | C7: =C6 | D7: =D6 | E7: =E6 | F7: =F6 | G7: =G6 | H7: =H6 | I7: =I6 | J7: =J6 | ... N7: =N6 | O7: =SUM(C7:N7)
B8: 2. OPERATING CASH DISBURSEMENTS
B9: Vendor & Supplier Disbursements (COGS) | C9: ='03_12M_P&L_Forecast'!C16 | D9: ='03_12M_P&L_Forecast'!D16 | E9: ='03_12M_P&L_Forecast'!E16 | F9: ='03_12M_P&L_Forecast'!F16 | G9: ='03_12M_P&L_Forecast'!G16 | H9: ='03_12M_P&L_Forecast'!H16 | I9: ='03_12M_P&L_Forecast'!I16 | J9: ='03_12M_P&L_Forecast'!J16 | ... N9: ='03_12M_P&L_Forecast'!N16 | O9: =SUM(C9:N9)
B10: Payroll, Salaries & Staff Benefits | C10: ='03_12M_P&L_Forecast'!C20 | D10: ='03_12M_P&L_Forecast'!D20 | E10: ='03_12M_P&L_Forecast'!E20 | F10: ='03_12M_P&L_Forecast'!F20 | G10: ='03_12M_P&L_Forecast'!G20 | H10: ='03_12M_P&L_Forecast'!H20 | I10: ='03_12M_P&L_Forecast'!I20 | J10: ='03_12M_P&L_Forecast'!J20 | ... N10: ='03_12M_P&L_Forecast'!N20 | O10: =SUM(C10:N10)
B11: Marketing & Customer Acquisition Outflows | C11: ='03_12M_P&L_Forecast'!C21 | D11: ='03_12M_P&L_Forecast'!D21 | E11: ='03_12M_P&L_Forecast'!E21 | F11: ='03_12M_P&L_Forecast'!F21 | G11: ='03_12M_P&L_Forecast'!G21 | H11: ='03_12M_P&L_Forecast'!H21 | I11: ='03_12M_P&L_Forecast'!I21 | J11: ='03_12M_P&L_Forecast'!J21 | ... N11: ='03_12M_P&L_Forecast'!N21 | O11: =SUM(C11:N11)
B12: Facilities, Software & General OpEx | C12: =SUM('03_12M_P&L_Forecast'!C22:C26) | D12: =SUM('03_12M_P&L_Forecast'!D22:D26) | E12: =SUM('03_12M_P&L_Forecast'!E22:E26) | F12: =SUM('03_12M_P&L_Forecast'!F22:F26) | G12: =SUM('03_12M_P&L_Forecast'!G22:G26) | H12: =SUM('03_12M_P&L_Forecast'!H22:H26) | I12: =SUM('03_12M_P&L_Forecast'!I22:I26) | J12: =SUM('03_12M_P&L_Forecast'!J22:J26) | ... N12: =SUM('03_12M_P&L_Forecast'!N22:N26) | O12: =SUM(C12:N12)
B13: Corporate Tax Payments | C13: ='03_12M_P&L_Forecast'!C31 | D13: ='03_12M_P&L_Forecast'!D31 | E13: ='03_12M_P&L_Forecast'!E31 | F13: ='03_12M_P&L_Forecast'!F31 | G13: ='03_12M_P&L_Forecast'!G31 | H13: ='03_12M_P&L_Forecast'!H31 | I13: ='03_12M_P&L_Forecast'!I31 | J13: ='03_12M_P&L_Forecast'!J31 | ... N13: ='03_12M_P&L_Forecast'!N31 | O13: =SUM(C13:N13)
B14: TOTAL OPERATING CASH OUTFLOWS | C14: =SUM(C9:C13) | D14: =SUM(D9:D13) | E14: =SUM(E9:E13) | F14: =SUM(F9:F13) | G14: =SUM(G9:G13) | H14: =SUM(H9:H13) | I14: =SUM(I9:I13) | J14: =SUM(J9:J13) | ... O14: =SUM(O9:O13)
B15: NET CASH FLOW FROM OPERATIONS (CFO) | C15: =C7-C14 | D15: =D7-D14 | E15: =E7-E14 | F15: =F7-F14 | G15: =G7-G14 | H15: =H7-H14 | I15: =I7-I14 | J15: =J7-J14 | ... O15: =O7-O14
B16: 3. INVESTING & FINANCING ACTIVITIES
B17: Capital Expenditures (CapEx & Hardware) | C17: 0 | D17: 0 | E17: 0 | F17: 0 | G17: ='02_Assumptions_&_Drivers'!$D$42 | H17: 0 | I17: 0 | J17: 0 | K17: 0 | L17: ='02_Assumptions_&_Drivers'!$D$43 | M17: 0 | N17: 0 | O17: =SUM(C17:N17)
B18: Financing / Capital Infusions / Loans | C18: 0 | D18: 0 | E18: 0 | F18: 0 | G18: 0 | H18: 0 | I18: 0 | J18: 0 | K18: 0 | L18: 0 | M18: 0 | N18: 0 | O18: =SUM(C18:N18)
B19: NET MONTHLY CASH CHANGE (BURN / BUILD) | C19: =C15-C17+C18 | D19: =D15-D17+D18 | E19: =E15-E17+E18 | F19: =F15-F17+F18 | G19: =G15-G17+G18 | H19: =H15-H17+H18 | I19: =I15-I17+I18 | J19: =J15-J17+J18 | ... O19: =O15-O17+O18
B20: 4. CASH LIQUIDITY & RUNWAY MONITORING
B21: Beginning Cash Balance | C21: ='02_Assumptions_&_Drivers'!$D$37 | D21: =C22 | E21: =D22 | F21: =E22 | G21: =F22 | H21: =G22 | I21: =H22 | J21: =I22 | K21: =J22 | ... N21: =M22 | O21: =C21
B22: ENDING CASH BALANCE | C22: =C21+C19 | D22: =D21+D19 | E22: =E21+E19 | F22: =F21+F19 | G22: =G21+G19 | H22: =H21+H19 | I22: =I21+I19 | J22: =J21+J19 | ... N22: =N21+N19 | O22: =N22
B23: Estimated Cash Runway (Months) | C23: =IF(C19<0, ROUND(C22/ABS(C19), 1), "Self-Sustaining") | D23: =IF(D19<0, ROUND(D22/ABS(D19), 1), "Self-Sustaining") | E23: =IF(E19<0, ROUND(E22/ABS(E19), 1), "Self-Sustaining") | F23: =IF(F19<0, ROUND(F22/ABS(F19), 1), "Self-Sustaining") | G23: =IF(G19<0, ROUND(G22/ABS(G19), 1), "Self-Sustaining") | H23: =IF(H19<0, ROUND(H22/ABS(H19), 1), "Self-Sustaining") | I23: =IF(I19<0, ROUND(I22/ABS(I19), 1), "Self-Sustaining") | J23: =IF(J19<0, ROUND(J22/ABS(J19), 1), "Self-Sustaining") | ... N23: =IF(N19<0, ROUND(N22/ABS(N19), 1), "Self-Sustaining") | O23: =N23

Sheet 05_Budget_vs_Actuals
A1: BUDGET VS. ACTUALS (BVA) VARIANCE ANALYSIS FRAMEWORK
A2: Financial Control Framework: 12M Budget vs Projected Actuals, Variance ($ and %), and Management Triggers
B4: Line Item / Category | C4: Account Code | D4: 12M Approved Budget | E4: Projected Actuals | F4: Variance ($) | G4: Variance (%) | H4: Performance Status | I4: Operational Action Required
B5: SaaS Subscriptions (Pro Tier) | C5: REV-4001 | D5: ='03_12M_P&L_Forecast'!O6 | E5: 365000 | F5: =E5-D5 | G5: =F5/D5 | H5: =IF(G5>=0, "FAVORABLE", IF(G5>=-0.05, "ON TRACK", "UNFAVORABLE")) | I5: Maintain high customer retention & upsell campaigns
B6: Enterprise Platform Licenses | C6: REV-4002 | D6: ='03_12M_P&L_Forecast'!O7 | E6: 585000 | F6: =E6-D6 | G6: =F6/D6 | H6: =IF(G6>=0, "FAVORABLE", IF(G6>=-0.05, "ON TRACK", "UNFAVORABLE")) | I6: Enterprise sales cycle outperforming budget by 12%
B7: Professional Implementation | C7: REV-4003 | D7: ='03_12M_P&L_Forecast'!O8 | E7: 420000 | F7: =E7-D7 | G7: =F7/D7 | H7: =IF(G7>=0, "FAVORABLE", IF(G7>=-0.05, "ON TRACK", "UNFAVORABLE")) | I7: Capacity bottleneck; add senior integration consultant
B8: Premium Managed Services & SLA | C8: REV-4004 | D8: ='03_12M_P&L_Forecast'!O9 | E8: 280000 | F8: =E8-D8 | G8: =F8/D8 | H8: =IF(G8>=0, "FAVORABLE", IF(G8>=-0.05, "ON TRACK", "UNFAVORABLE")) | I8: Renewals on schedule; stable recurring cash flows
B9: Direct Hosting & Cloud (COGS) | C9: COS-5001 | D9: ='03_12M_P&L_Forecast'!O12 | E9: 48500 | F9: =D9-E9 | G9: =F9/D9 | H9: =IF(G9>=0, "FAVORABLE", IF(G9>=-0.05, "ON TRACK", "UNFAVORABLE")) | I9: Reserve multi-year AWS instances to trim unit costs
B10: Royalties & Third-Party APIs (COGS) | C10: COS-5002 | D10: ='03_12M_P&L_Forecast'!O13 | E10: 102000 | F10: =D10-E10 | G10: =F10/D10 | H10: =IF(G10>=0, "FAVORABLE", IF(G10>=-0.05, "ON TRACK", "UNFAVORABLE")) | I10: Renegotiate API rate limits with key LLM/data vendors
B11: Contract Engineering (COGS) | C11: COS-5003 | D11: ='03_12M_P&L_Forecast'!O14 | E11: 155000 | F11: =D11-E11 | G11: =F11/D11 | H11: =IF(G11>=0, "FAVORABLE", IF(G11>=-0.05, "ON TRACK", "UNFAVORABLE")) | I11: In-source recurring tasks to lower external billables
B12: Support Engineering & SLA (COGS) | C12: COS-5004 | D12: ='03_12M_P&L_Forecast'!O15 | E12: 58000 | F12: =D12-E12 | G12: =F12/D12 | H12: =IF(G12>=0, "FAVORABLE", IF(G12>=-0.05, "ON TRACK", "UNFAVORABLE")) | I12: Automation deflection reduced tier-1 ticket volume
B13: Salaries, Wages & Benefits | C13: OPX-6001 | D13: ='03_12M_P&L_Forecast'!O20 | E13: 475000 | F13: =D13-E13 | G13: =F13/D13 | H13: =IF(G13>=0, "FAVORABLE", IF(G13>=-0.05, "ON TRACK", "UNFAVORABLE")) | I13: Headcount ramp delayed by 3 weeks; favorable cost save
B14: Paid Digital Marketing & Ads | C14: OPX-6002 | D14: ='03_12M_P&L_Forecast'!O21 | E14: 68000 | F14: =D14-E14 | G14: =F14/D14 | H14: =IF(G14>=0, "FAVORABLE", IF(G14>=-0.05, "ON TRACK", "UNFAVORABLE")) | I14: CAC increased in Q2; reallocating spend to LinkedIn B2B
B15: Cloud Infrastructure (Internal) | C15: OPX-6003 | D15: ='03_12M_P&L_Forecast'!O22 | E15: 34000 | F15: =D15-E15 | G15: =F15/D15 | H15: =IF(G15>=0, "FAVORABLE", IF(G15>=-0.05, "ON TRACK", "UNFAVORABLE")) | I15: Dev/test server cluster clean-up completed
B16: Software Subscriptions & SaaS Tools | C16: OPX-6004 | D16: ='03_12M_P&L_Forecast'!O23 | E16: 23500 | F16: =D16-E16 | G16: =F16/D16 | H16: =IF(G16>=0, "FAVORABLE", IF(G16>=-0.05, "ON TRACK", "UNFAVORABLE")) | I16: Audit software licenses; eliminate duplicate seats
B17: Office Lease & Facilities | C17: OPX-6005 | D17: ='03_12M_P&L_Forecast'!O24 | E17: 38400 | F17: =D17-E17 | G17: =F17/D17 | H17: =IF(G17>=0, "FAVORABLE", IF(G17>=-0.05, "ON TRACK", "UNFAVORABLE")) | I17: Fixed multi-year lease agreement; on target
B18: Legal, Audit & Professional | C18: OPX-6006 | D18: ='03_12M_P&L_Forecast'!O25 | E18: 22000 | F18: =D18-E18 | G18: =F18/D18 | H18: =IF(G18>=0, "FAVORABLE", IF(G18>=-0.05, "ON TRACK", "UNFAVORABLE")) | I18: Unbudgeted trademark filing fees in Q3
B19: Travel & Business Development | C19: OPX-6007 | D19: ='03_12M_P&L_Forecast'!O26 | E19: 18500 | F19: =D19-E19 | G19: =F19/D19 | H19: =IF(G19>=0, "FAVORABLE", IF(G19>=-0.05, "ON TRACK", "UNFAVORABLE")) | I19: Executive travel capped; pivot to virtual demos

Sheet 06_Data_Cleaning_Pipeline
A1: AUTOMATED FINANCIAL DATA INGESTION & CLEANSING PIPELINE
A2: Demonstrating Full ETL Transformation: Raw Messy Accounting Ledger -> Automated Audit Trail -> Clean Financial Standard
B4: PIPELINE ARCHITECTURE: Ingests unstructured ERP/Bank journal extracts, resolves entity aliases, parses mixed dates/currencies, removes duplicates, and maps Chart of Accounts into model drivers.
B6: STAGE 1: RAW UNSTRUCTURED ERP JOURNAL EXTRACT (MESSY SOURCE) | H6: STAGE 2: CLEAN AUDITED LEDGER (DASHBOARD & MODEL READY)
B7: Raw Tx ID | C7: Raw Date Stamp | D7: Raw Counterparty / Vendor | E7: Raw Amount String | F7: Raw Account Code | H7: Clean Tx ID | I7: ISO Posting Date | J7: Master Counterparty | K7: Clean Amount ($) | L7: Standard GL Category
B8: TX-9021 | C8: 2026/01/14 | D8: amazon web services inc | E8: $ 4,250.00 USD | F8: NULL | H8: TX-9021 | I8: 2026-01-14 | J8: Amazon Web Services (AWS) | K8: 4250 | L8: Cloud Infrastructure (COGS)
B9: TX-9022 | C9: 14-Jan-2026 | D9: AWS CLOUD SVCS | E9: (4,250.00) | F9: 6002-ops | H9: TX-9022 | I9: 2026-01-14 | J9: Amazon Web Services (AWS) | K9: 4250 | L9: Cloud Infrastructure (COGS)
B10: TX-9023 | C10: 2026.01.18 | D10: MICROSOFT IRELAND / AZURE | E10: 1280.50 $ | F10: 6004-sub | H10: TX-9023 | I10: 2026-01-18 | J10: Microsoft Azure Cloud | K10: 1280.5 | L10: Software SaaS Subscriptions
B11: TX-9024 | C11: 01/22/2026 | D11: google *workspace gsuite | E11: $ 640.00 | F11: gsuite | H11: TX-9024 | I11: 2026-01-22 | J11: Google Workspace | K11: 640 | L11: Software SaaS Subscriptions
B12: TX-9025 | C12: 2026-01-25 | D12: Stripe Inc (Payment Processing) | E12: 1820.00 USD | F12: rev-proc | H12: TX-9025 | I12: 2026-01-25 | J12: Stripe Payment Gateway | K12: 1820 | L12: Payment Gateway Fees (COGS)
B13: TX-9026 | C13: 25/01/2026 | D13: STRIPE PAYMENTS | E13: $1,820.00 | F13: COGS-30 | H13: TX-9026 | I13: 2026-01-25 | J13: Stripe Payment Gateway | K13: 1820 | L13: Payment Gateway Fees (COGS)
B14: TX-9027 | C14: 2026-02-02 | D14: WeWork Global Management LLC | E14: $3,200.00 | F14: RENT-HQ | H14: TX-9027 | I14: 2026-02-02 | J14: WeWork HQ Facilities | K14: 3200 | L14: Office Lease & Facilities
B15: TX-9028 | C15: 2026-02-10 | D15: Gartner Advisory Group | E15: $ 12,500.00 | F15: CONSULT | H15: TX-9028 | I15: 2026-02-10 | J15: Gartner Advisory Services | K15: 12500 | L15: Legal, Audit & Professional
B16: TX-9029 | C16: 2026-02-15 | D16: LINKEDIN MARKETING SOL | E16: $ 2,850.00 | F16: MKT-AD | H16: TX-9029 | I16: 2026-02-15 | J16: LinkedIn B2B Advertising | K16: 2850 | L16: Paid Digital Marketing & Ads
B17: TX-9030 | C17: VOID-TRANS | D17: Duplicate VOID Entry | E17: $ 0.00 | F17: VOID | H17: TX-9030 | I17: FILTERED | J17: [REMOVED: VOID / DUPLICATE] | K17: 0 | L17: [EXCLUDED FROM P&L]
B18: TX-9031 | C18: 2026-02-28 | D18: ADP TotalSource Payroll Tax | E18: $ 42,500.00 | F18: PAYROLL | H18: TX-9031 | I18: 2026-02-28 | J18: ADP Payroll & Tax Solutions | K18: 42500 | L18: Salaries, Wages & Benefits
B19: TX-9032 | C19: 2026-03-05 | D19: Slack Technologies / Salesforce | E19: $ 850.00 | F19: 6004 | H19: TX-9032 | I19: 2026-03-05 | J19: Slack Technologies / Salesforce | K19: 850 | L19: Software SaaS Subscriptions
B22: AUDITABLE ETL & DATA HYGIENE SPECIFICATION APPLIED IN MODEL
B23: Step 1: String Trimming & Deduplication | E23: Stripped leading/trailing ASCII whitespace and newline characters from Transaction IDs and Counterparty strings; flagged void duplicates.
B24: Step 2: Universal Date Normalization | E24: Parsed 4 heterogeneous date formats ('YYYY/MM/DD', 'DD-MMM-YYYY', 'MM/DD/YYYY', 'YYYY.MM.DD') into ISO 8601 standard (YYYY-MM-DD).
B25: Step 3: Fuzzy Entity Resolution | E25: Normalized vendor aliases ('AWS CLOUD SVCS', 'amazon web services inc') into unified Master Counterparty 'Amazon Web Services (AWS)'.
B26: Step 4: Financial String Sanitization | E26: Removed currency characters ('$', 'USD'), stripped commas, resolved accounting parentheses '(4,250.00)' into positive debit expenses.
B27: Step 5: Chart of Accounts (COA) Mapping | E27: Mapped unclassified GL codes ('6002-ops', 'NULL', 'gsuite') into structured P&L Expense Drivers (Cloud COGS, SaaS, Facilities).

Sheet 07_Model_Documentation
A1: FINANCIAL MODEL DOCUMENTATION & OPERATIONAL GUIDEBOOK
A2: Architecture Principles, Color Codes, Formula Audit Trails & Monthly Maintenance Procedures
B5: 1. MODEL ARCHITECTURE & FINANCIAL LOGIC
B6: Dynamic Three-Tier Linkage | C6: All financial statements (P&L, Cash Flow, BvA) dynamically cascade from '02_Assumptions_&_Drivers'. No numbers are hardcoded within calculation tabs.
B7: FAST Standard Color Legend | C7: Blue text with soft-green background indicates an editable assumption. Black text with standard borders indicates a formula cell that should NOT be overwritten.
B8: Direct Method Cash Flow | C8: Operating cash collections model 30-day DSO customer payment lag. Operating disbursements reflect realistic 30-day vendor lag to prevent cash surprise.
B10: 2. MONTHLY UPDATE & CLOSE PROCEDURES
B11: Step 1: Input Actuals | C11: Open sheet '05_Budget_vs_Actuals' at month close. Enter actual revenue and expenses into Column E (soft green cells).
B12: Step 2: Review Variance Flags | C12: Inspect Column H for 'UNFAVORABLE' alerts (>5% adverse variance) and record operational mitigation actions in Column I.
B13: Step 3: Update Hiring Roster | C13: If planned employee start dates change, adjust Column E ('Start Month') in '02_Assumptions_&_Drivers' to recalculate payroll.
B14: Step 4: Present Executive Scorecard | C14: The '01_Executive_Dashboard' automatically refreshes quarterly KPIs, chart visualizations, and ending liquidity.
B16: 3. KEY PERFORMANCE RATIO DEFINITIONS
B17: Gross Margin % | C17: Gross Profit divided by Gross Revenue. Measures unit profitability before fixed operational overhead.
B18: EBITDA | C18: Earnings Before Interest, Taxes, Depreciation, and Amortization. Evaluates pure core operational cash profitability.
B19: Cash Runway | C19: Ending Cash Balance divided by Net Monthly Burn. Indicates remaining operational runway before capital depletion.
B20: Days Sales Outstanding (DSO) | C20: Average number of days required to collect cash payments following invoice issuance (assumed at 30 days).
