Workbook

Sheet 01_Field_Scope_Estimator
A1: GREATER D.C. PROPERTY TRANSITION & INSTANT SCOPE ESTIMATOR
A2: Proprietary Decision Engine: On-Site Parametric Estimator, 21-Day Transition Budgets & Value-Add ROI
B5: STEP 1: ON-SITE PROPERTY INPUTS & MARKET SELECTION
B6: Target Property Address: | C6: 1420 14th Street NW, Washington, D.C. | F6: Identified Submarket: | I6: =XLOOKUP(C7,'03_Parametric_Rules_Multipliers'!$B$7:$B$22,'03_Parametric_Rules_Multipliers'!$C$7:$C$22&" ("&'03_Parametric_Rules_Multipliers'!$D$7:$D$22&")","Unknown ZIP")
B7: Target ZIP Code (D.C. Metro): | C7: 20001 | F7: Regional Labor Multiplier: | I7: =XLOOKUP(C7,'03_Parametric_Rules_Multipliers'!$B$7:$B$22,'03_Parametric_Rules_Multipliers'!$E$7:$E$22,1.0)
B8: Property Square Footage (SF): | C8: 1850 | F8: Median Days on Market (MDOM): | I8: =XLOOKUP(C7,'03_Parametric_Rules_Multipliers'!$B$7:$B$22,'03_Parametric_Rules_Multipliers'!$F$7:$F$22,21)&" Days"
B9: Selected Asset Tier: | C9: Better | F9: Operational Speed Zone: | I9: =XLOOKUP(C7,'03_Parametric_Rules_Multipliers'!$B$7:$B$22,'03_Parametric_Rules_Multipliers'!$G$7:$G$22,"Standard")
B11: TOTAL ESTIMATED TRANSITION SCOPE | D11: AVERAGE COST PER SQUARE FOOT | F11: ESTIMATED VALUE-ADD EQUITY LIFT | H11: PROJECTED VALUE-ADD / ROI MULTIPLE | J11: ESTIMATED TARGET COMPLETION
B12: =I22 | D12: =I22/C8 | F12: =K23 | H12: =K24 | J12: ="21 Business Days"
B13: Includes Labor, Materials & Multipliers | D13: Comprehensive $/SF investment | F13: Projected Net Equity Spread | H13: Benchmark: 1.8x - 2.0x target | J13: Guaranteed 21-Day Cosmetic Turn
B15: STEP 2: 21-DAY COSMETIC TRANSITION SCOPE BUILDER (PARAMETRIC SELECTOR)
B16: Include in Scope? | C16: Scope Line Item / Package | D16: Execution Category | E16: Base Scope Qty / Unit | F16: Selected SKU Code | G16: Material Unit Rate | H16: Labor Unit Rate | I16: Regional Scope Cost | J16: Target ROI Multiple | K16: Projected Value-Add ($)
B17: YES | C17: Whole-Home Decluttering & Staging Prep | D17: Decluttering | E17: =C8 | F17: SKU-DEC-102 | G17: =IF($C$9="Good", XLOOKUP(F17,'02_Master_SKU_Database'!$B$6:$B$20,'02_Master_SKU_Database'!$G$6:$G$20,0), IF($C$9="Best", XLOOKUP(F17,'02_Master_SKU_Database'!$B$6:$B$20,'02_Master_SKU_Database'!$I$6:$I$20,0), XLOOKUP(F17,'02_Master_SKU_Database'!$B$6:$B$20,'02_Master_SKU_Database'!$H$6:$H$20,0))) | H17: =XLOOKUP(F17,'02_Master_SKU_Database'!$B$6:$B$20,'02_Master_SKU_Database'!$J$6:$J$20,0)*$I$7 | I17: =IF(B17="YES", E17*(G17+H17), 0) | J17: ='03_Parametric_Rules_Multipliers'!$E$35 | K17: =I17*J17
B18: YES | C18: Interior Paint, Drywall & Trim Modernization | D18: Paint | E18: =C8 | F18: SKU-PNT-201 | G18: =IF($C$9="Good", XLOOKUP(F18,'02_Master_SKU_Database'!$B$6:$B$20,'02_Master_SKU_Database'!$G$6:$G$20,0), IF($C$9="Best", XLOOKUP(F18,'02_Master_SKU_Database'!$B$6:$B$20,'02_Master_SKU_Database'!$I$6:$I$20,0), XLOOKUP(F18,'02_Master_SKU_Database'!$B$6:$B$20,'02_Master_SKU_Database'!$H$6:$H$20,0))) | H18: =XLOOKUP(F18,'02_Master_SKU_Database'!$B$6:$B$20,'02_Master_SKU_Database'!$J$6:$J$20,0)*$I$7 | I18: =IF(B18="YES", E18*(G18+H18), 0) | J18: ='03_Parametric_Rules_Multipliers'!$E$36 | K18: =I18*J18
B19: YES | C19: Continuous Waterproof LVP / Hardwood Flooring | D19: Flooring | E19: =C8*0.75 | F19: SKU-FLR-301 | G19: =IF($C$9="Good", XLOOKUP(F19,'02_Master_SKU_Database'!$B$6:$B$20,'02_Master_SKU_Database'!$G$6:$G$20,0), IF($C$9="Best", XLOOKUP(F19,'02_Master_SKU_Database'!$B$6:$B$20,'02_Master_SKU_Database'!$I$6:$I$20,0), XLOOKUP(F19,'02_Master_SKU_Database'!$B$6:$B$20,'02_Master_SKU_Database'!$H$6:$H$20,0))) | H19: =XLOOKUP(F19,'02_Master_SKU_Database'!$B$6:$B$20,'02_Master_SKU_Database'!$J$6:$J$20,0)*$I$7 | I19: =IF(B19="YES", E19*(G19+H19), 0) | J19: ='03_Parametric_Rules_Multipliers'!$E$37 | K19: =I19*J19
B20: YES | C20: Cabinet Pulls & Contemporary Plumbing Fixtures | D20: Hardware | E20: 1 | F20: SKU-HRD-401 | G20: =IF($C$9="Good", XLOOKUP(F20,'02_Master_SKU_Database'!$B$6:$B$20,'02_Master_SKU_Database'!$G$6:$G$20,0), IF($C$9="Best", XLOOKUP(F20,'02_Master_SKU_Database'!$B$6:$B$20,'02_Master_SKU_Database'!$I$6:$I$20,0), XLOOKUP(F20,'02_Master_SKU_Database'!$B$6:$B$20,'02_Master_SKU_Database'!$H$6:$H$20,0))) | H20: =XLOOKUP(F20,'02_Master_SKU_Database'!$B$6:$B$20,'02_Master_SKU_Database'!$J$6:$J$20,0)*$I$7 | I20: =IF(B20="YES", E20*(G20+H20), 0) | J20: ='03_Parametric_Rules_Multipliers'!$E$38 | K20: =I20*J20
B21: YES | C21: Designer 3000K LED Recessed & Accent Lighting | D21: Lighting | E21: 1 | F21: SKU-LGT-501 | G21: =IF($C$9="Good", XLOOKUP(F21,'02_Master_SKU_Database'!$B$6:$B$20,'02_Master_SKU_Database'!$G$6:$G$20,0), IF($C$9="Best", XLOOKUP(F21,'02_Master_SKU_Database'!$B$6:$B$20,'02_Master_SKU_Database'!$I$6:$I$20,0), XLOOKUP(F21,'02_Master_SKU_Database'!$B$6:$B$20,'02_Master_SKU_Database'!$H$6:$H$20,0))) | H21: =XLOOKUP(F21,'02_Master_SKU_Database'!$B$6:$B$20,'02_Master_SKU_Database'!$J$6:$J$20,0)*$I$7 | I21: =IF(B21="YES", E21*(G21+H21), 0) | J21: ='03_Parametric_Rules_Multipliers'!$E$39 | K21: =I21*J21
B22: TOTAL 21-DAY ESTIMATED TRANSITION SCOPE INVESTMENT | I22: =SUM(I17:I21) | J22: =K23/I22 | K22: =SUM(K17:K21)
B23: NET PROJECTED EQUITY CREATION / PROFIT SPREAD (VALUE-ADD MINUS SCOPE COST) | K23: =K22-I22
B24: BLENDED PORTFOLIO VALUE-ADD MULTIPLE (ARV LIFT ÷ SCOPE INVESTMENT) | K24: =K22/I22

Sheet 02_Master_SKU_Database
A1: MASTER SKU & MATERIAL PRICE DATABASE (LIVE SOURCING FEED)
A2: Structured Procurement Catalog: Home Depot, Floor & Decor, Amazon Commercial Rates ($/SF, $/EA)
B5: SKU ID | C5: Scope Category | D5: Material / Item Description | E5: Preferred Sourcing Vendor | F5: Unit Measure | G5: Good Spec ($) | H5: Better Spec ($) | I5: Best Spec ($) | J5: Labor Install Rate ($/Unit) | K5: Catalog Status
B6: SKU-DEC-101 | C6: Decluttering | D6: Professional Junk Removal & 20-Yard Roll-off Dumpster | E6: 1-800-Got-Junk / Local | F6: EA (Drop) | G6: 450 | H6: 650 | I6: 950 | J6: 300 | K6: ACTIVE
B7: SKU-DEC-102 | C7: Decluttering | D7: Professional Staging Preparation, Deep Clean & Window Polish | E7: Commercial Clean Pro | F7: SF | G7: 0.35 | H7: 0.55 | I7: 0.85 | J7: 0.2 | K7: ACTIVE
B8: SKU-PNT-201 | C8: Paint | D8: Interior Wall Paint (Sherwin Williams / Behr Premium) | E8: Home Depot Pro | F8: SF (Floor) | G8: 1.2 | H8: 1.65 | I8: 2.4 | J8: 1.5 | K8: ACTIVE
B9: SKU-PNT-202 | C9: Paint | D9: Trim, Baseboard, Door & Ceiling Ultra-Pure White Enamel | E9: Sherwin Williams Comm | F9: SF (Floor) | G9: 0.6 | H9: 0.85 | I9: 1.25 | J9: 0.75 | K9: ACTIVE
B10: SKU-FLR-301 | C10: Flooring | D10: Rigid Core Waterproof Luxury Vinyl Plank (LVP - 20mil Wear) | E10: Floor & Decor | F10: SF | G10: 2.29 | H10: 3.49 | I10: 4.99 | J10: 2.25 | K10: ACTIVE
B11: SKU-FLR-302 | C11: Flooring | D11: Engineered European White Oak Hardwood Flooring | E11: Floor & Decor Pro | F11: SF | G11: 3.99 | H11: 5.89 | I11: 8.99 | J11: 3.5 | K11: ACTIVE
B12: SKU-FLR-303 | C12: Flooring | D12: Premium Stain-Resistant Carpet & 8lb Memory Foam Pad | E12: Home Depot Comm | F12: SF | G12: 1.85 | H12: 2.75 | I12: 4.1 | J12: 1.15 | K12: ACTIVE
B13: SKU-HRD-401 | C13: Hardware | D13: Modern Matte Black / Brushed Gold Cabinet Pulls (30-Pack) | E13: Amazon Business | F13: Set (Kitchen) | G13: 65 | H13: 120 | I13: 220 | J13: 150 | K13: ACTIVE
B14: SKU-HRD-402 | C14: Hardware | D14: Contemporary High-Arc Pull-Down Commercial Kitchen Faucet | E14: Home Depot Pro | F14: EA | G14: 119 | H14: 229 | I14: 399 | J14: 175 | K14: ACTIVE
B15: SKU-HRD-403 | C15: Hardware | D15: Single-Hole Matte Black Bathroom Faucets & Pop-Up Drains | E15: Amazon Commercial | F15: EA | G15: 59 | H15: 115 | I15: 210 | J15: 120 | K15: ACTIVE
B16: SKU-HRD-404 | C16: Hardware | D16: Modern Interior Door Lever Handles & Privacy Latches | E16: Home Depot Pro | F16: EA (Door) | G16: 18.5 | H16: 32 | I16: 58 | J16: 25 | K16: ACTIVE
B17: SKU-LGT-501 | C17: Lighting | D17: Ultra-Thin Dimmable 6-Inch Canless LED Recessed Lights (Pack of 12) | E17: Amazon Business | F17: Pack | G17: 110 | H17: 185 | I17: 295 | J17: 180 | K17: ACTIVE
... B20: SKU-LGT-504 | C20: Lighting | D20: Smart Wi-Fi Rocker Light Switches & Decora Wall Plates | E20: Lutron / Amazon | F20: Set (Whole) | G20: 85 | H20: 175 | I20: 320 | J20: 140 | K20: ACTIVE

Sheet 03_Parametric_Rules_Multipliers
A1: PARAMETRIC RULES & REGIONAL TIER MULTIPLIERS (ENGINE LOGIC)
A2: Centralized Formula Logic: Greater D.C. Submarket Multipliers, Speed Zones & ROI Benchmark Multiples
B5: 1. GREATER D.C. SUBMARKET MATRIX & REGIONAL MULTIPLIERS
B6: Target ZIP Code | C6: Submarket / Neighborhood | D6: State / Jurisdiction | E6: Labor & Market Multiplier | F6: Historical MDOM (Days) | G6: Operational Speed Zone
B7: 20001 | C7: Shaw / Logan Circle / Mt Vernon | D7: Washington, D.C. | E7: 1.25 | F7: 12 | G7: Alpha Zone (Ultra-Fast)
B8: 20007 | C8: Georgetown / Glover Park | D8: Washington, D.C. | E8: 1.45 | F8: 11 | G8: Alpha Zone (Ultra-Fast)
B9: 20002 | C9: Capitol Hill / H-Street Corridor | D9: Washington, D.C. | E9: 1.2 | F9: 15 | G9: Beta Zone (Standard)
B10: 20009 | C10: Dupont Circle / Adams Morgan | D10: Washington, D.C. | E10: 1.35 | F10: 13 | G10: Alpha Zone (Ultra-Fast)
B11: 20016 | C11: Tenleytown / AU Park / Spring Valley | D11: Washington, D.C. | E11: 1.4 | F11: 14 | G11: Alpha Zone (Ultra-Fast)
B12: 22201 | C12: Clarendon / Courthouse / Rosslyn | D12: Arlington, VA | E12: 1.3 | F12: 9 | G12: Alpha Zone (Ultra-Fast)
B13: 22207 | C13: North Arlington / Country Club | D13: Arlington, VA | E13: 1.45 | F13: 10 | G13: Alpha Zone (Ultra-Fast)
B14: 22314 | C14: Old Town Alexandria | D14: Alexandria, VA | E14: 1.28 | F14: 16 | G14: Beta Zone (Standard)
B15: 22101 | C15: McLean / Salona Village | D15: Fairfax County, VA | E15: 1.55 | F15: 12 | G15: Alpha Zone (Ultra-Fast)
B16: 22182 | C16: Vienna / Tysons Corner | D16: Fairfax County, VA | E16: 1.25 | F16: 14 | G16: Alpha Zone (Ultra-Fast)
B17: 20190 | C17: Reston Town Center / Dulles Corridor | D17: Fairfax County, VA | E17: 1.15 | F17: 22 | G17: Beta Zone (Standard)
B18: 20814 | C18: Bethesda / Downtown Arts District | D18: Montgomery Co, MD | E18: 1.4 | F18: 11 | G18: Alpha Zone (Ultra-Fast)
... B22: 20782 | C22: Hyattsville / Gateway Arts | D22: Prince George's, MD | E22: 1 | F22: 38 | G22: Gamma Zone (Extended)
B25: 2. ASSET SPECIFICATION TIERS & GRADE MULTIPLIERS
B26: Asset Tier Code | C26: Asset Tier Description | D26: Price Band Benchmark | E26: Specification Grade | F26: Finish Tier Multiplier
B27: Good | C27: Good (< $500k Market Value) | D27: < $500,000 USD | E27: Clean Rental / Entry Spec (LVP, Builder Fixtures) | F27: 1
B28: Better | C28: Better ($500k - $799k Market Value) | D28: $500,000 - $799,999 USD | E28: Move-In Retail Spec (Wide Plank LVP, Matte Black) | F28: 1.25
B29: Best | C29: Best ($800k+ Executive Portfolio) | D29: $800,000+ USD | E29: Luxury Turnkey Spec (Engineered Oak, Designer Brass) | F29: 1.6
B31: 3. 21-DAY COSMETIC VALUE-ADD & VALUE-CREATION ROI BENCHMARKS
B32: Scope Category ID | C32: Scope Category Name | D32: Execution Window | E32: Typical Value-Add Multiple | F32: Market Strategic Rationale
B33: SCP-01 | C33: Whole-Home Decluttering & Staging Prep | D33: Days 1 - 4 | E33: 2.15 | F33: Highest direct ROI: eliminates visual friction; expands perceived SF
B34: SCP-02 | C34: Interior Paint, Trim & Drywall Refinish | D34: Days 5 - 10 | E34: 1.95 | F34: Neutral SW Alabaster/Agreeable Gray creates modern airy appeal
B35: SCP-03 | C35: Flooring Modernization (LVP / Hardwood) | D35: Days 11 - 16 | E35: 1.8 | F35: Removes dated carpet odor; unified continuous flooring visually doubles space
B36: SCP-04 | C36: Cabinet Hardware & Modern Plumbing Fixtures | D36: Days 15 - 18 | E36: 1.85 | F36: High-impact micro-refresh; elevates kitchens and baths at 1/10th remodel cost
B37: SCP-05 | C37: Designer LED Lighting & Fixture Upgrade | D37: Days 18 - 21 | E37: 1.9 | F37: Replaces 90s brass with 3000K warm LED lighting; photographs exceptionally
